{
  "Uuid": "96a230bf-d9cc-4de8-9e6a-fe895079c470",
  "PluginType": "phone",
  "Url": "https://calleridtest.com/",
  "Active": true,
  "GroupName": "Default",
  "Action": "CreateTab",
  "HomePage": "https://calleridtest.com/",
  "SupportPage": "https://calleridtest.com/",
  "UpdateUrl": null,
  "ExpiresOn": null,
  "Description": null,
  "Label": "Caller Id",
  "ReadOnly": false,
  "SortOrder": 0,
  "TimeOut": 100,
  "LastAccessedOn": null,
  "CreatedOn": "2025-01-11T13:52:11.313",
  "TimeTaken": 0,
  "DiscoveryToolSiteUuid": null,
  "DiscoveryPluginParentUuid": null,
  "Method": "GET",
  "Version": "1.0.0",
  "MimeTypeRegex": null,
  "Status": null,
  "ContentTypeHeader": null,
  "FieldMapping": {},
  "Headers": {},
  "Regex": null,
  "AuthorizationBearerToken": null,
  "AuthorizationUserName": null,
  "AuthorizationPassword": null,
  "EventType": null,
  "ForwardResponse": false,
  "Script": null,
  "Inputs": null,
  "Outputs": null
}